devtools_lorem_ipsum/__init__.py
devtools_lorem_ipsum-1.0.1.dist-info/METADATA
devtools_lorem_ipsum-1.0.1.dist-info/WHEEL
devtools_lorem_ipsum-1.0.1.dist-info/top_level.txt
devtools_lorem_ipsum-1.0.1.dist-info/RECORD
