Metadata-Version: 2.1
Name: devtools-lorem-ipsum
Version: 1.0.1
Summary: Lorem ipsum generator
Home-page: https://devtools.at/tools/lorem-ipsum
Author: DevTools.at
Author-email: hello@devtools.at
Project-URL: Homepage, https://devtools.at/tools/lorem-ipsum
Project-URL: Repository, https://github.com/devtools-at/lorem-ipsum
Classifier: Development Status :: 4 - Beta
Classifier: Intended Audience :: Developers
Classifier: License :: OSI Approved :: MIT License
Classifier: Programming Language :: Python :: 3
Requires-Python: >=3.8
